Metadata-Version: 2.1
Name: openpyxl-templates310
Version: 0.2.9
Summary: Openpyxl-templates is an extention to openpyxl which simplifies reading and writing excelfiles by formalizing their structure into templates.
Home-page: https://github.com/sillydan1/openpyxl-templates
Author: Sverker Sjöberg
License: MIT
Classifier: Development Status :: 3 - Alpha
Classifier: Intended Audience :: Developers
Classifier: License :: OSI Approved :: MIT License
Classifier: Operating System :: OS Independent
Classifier: Programming Language :: Python
Classifier: Programming Language :: Python :: 3
Classifier: Programming Language :: Python :: 3.4
Classifier: Programming Language :: Python :: 3.5
Classifier: Programming Language :: Python :: 3.6
Classifier: Programming Language :: Python :: 3.10
Classifier: Programming Language :: Python :: 3.11
Classifier: Programming Language :: Python :: Implementation :: PyPy
License-File: LICENSE
Requires-Dist: fortnum
Requires-Dist: future
Requires-Dist: openpyxl
